aws_ar/__init__.py
aws_ar/aws_ar.py
aws_ar-2.0.dist-info/METADATA
aws_ar-2.0.dist-info/WHEEL
aws_ar-2.0.dist-info/entry_points.txt
aws_ar-2.0.dist-info/top_level.txt
aws_ar-2.0.dist-info/RECORD
